ti/__init__.py
ti/ina238.py
ina238-0.0.2.dist-info/METADATA
ina238-0.0.2.dist-info/WHEEL
ina238-0.0.2.dist-info/RECORD
